basicrpc.py
binaryrpc.py
binaryrpc-0.1.0.dist-info/DESCRIPTION.rst
binaryrpc-0.1.0.dist-info/METADATA
binaryrpc-0.1.0.dist-info/RECORD
binaryrpc-0.1.0.dist-info/WHEEL
binaryrpc-0.1.0.dist-info/metadata.json
binaryrpc-0.1.0.dist-info/top_level.txt
binaryrpc-0.1.0.dist-info/zip-safe
